[
  {
    "id": "c4012468-ba20-43a6-99c5-1e8dbfb15175",
    "name": "Christie Kreiger",
    "phone": "524-544-6821 x66065",
    "email": "Jeremie_Raynor79@gmail.com",
    "job": "Dynamic Accountability Technician"
  },
  {
    "id": "4d54a810-1bea-453d-9d36-b9a082bd7a19",
    "name": "Dr. Drew Jacobson DVM",
    "phone": "895.922.8534 x085",
    "email": "Barrett.Goldner63@yahoo.com",
    "job": "Principal Research Facilitator"
  },
  {
    "id": "2f35bf78-0da0-4c37-af51-af86086904be",
    "name": "Jessie McKenzie",
    "phone": "335-562-7493 x4351",
    "email": "Ezekiel.Pfeffer@yahoo.com",
    "job": "Legacy Web Assistant"
  },
  {
    "id": "9f3123a3-1661-4308-82e6-7210d8ea935a",
    "name": "Kerry Orn",
    "phone": "1-733-423-1075 x963",
    "email": "Ahmed95@hotmail.com",
    "job": "Central Division Technician"
  },
  {
    "id": "51fc29e5-ff23-4aef-b73d-2f57d60c17a2",
    "name": "Lula Legros",
    "phone": "1-713-564-3942 x5162",
    "email": "Priscilla_Senger35@yahoo.com",
    "job": "Senior Factors Technician"
  }
]